{
  "schema_version": 1,
  "generated_at": "2026-07-13T13:26:02.493911+08:00",
  "generated_timezone": "Asia/Shanghai",
  "watchlist_path": "/Users/yuan/projects/market-regime-alpha/data/external/watchlists/dividend_t_watchlist.csv",
  "source": "local_csv_5min+tencent_minute_query_1min_to_5min",
  "horizon": "未来1/3/5日上涨概率与1/3/5日历史命中率",
  "point_hit_rates": {
    "status": "ok",
    "source": "/Users/yuan/projects/market-regime-alpha/reports/backtests/buy_sell_point_hit_rate_summary.csv",
    "rows": [
      {
        "point_type": "buy",
        "horizon_days": 1,
        "sample_count": 28,
        "hit_count": 19,
        "hit_rate": 0.6786,
        "average_future_return": 0.00395
      },
      {
        "point_type": "buy",
        "horizon_days": 3,
        "sample_count": 28,
        "hit_count": 16,
        "hit_rate": 0.5714,
        "average_future_return": 0.005529
      },
      {
        "point_type": "buy",
        "horizon_days": 5,
        "sample_count": 28,
        "hit_count": 20,
        "hit_rate": 0.7143,
        "average_future_return": 0.005286
      },
      {
        "point_type": "sell",
        "horizon_days": 1,
        "sample_count": 762,
        "hit_count": 414,
        "hit_rate": 0.5433,
        "average_future_return": -0.000624
      },
      {
        "point_type": "sell",
        "horizon_days": 3,
        "sample_count": 743,
        "hit_count": 440,
        "hit_rate": 0.5922,
        "average_future_return": -0.004443
      },
      {
        "point_type": "sell",
        "horizon_days": 5,
        "sample_count": 721,
        "hit_count": 415,
        "hit_rate": 0.5756,
        "average_future_return": -0.004814
      }
    ],
    "by_type": {
      "buy": {
        "1": {
          "point_type": "buy",
          "horizon_days": 1,
          "sample_count": 28,
          "hit_count": 19,
          "hit_rate": 0.6786,
          "average_future_return": 0.00395
        },
        "3": {
          "point_type": "buy",
          "horizon_days": 3,
          "sample_count": 28,
          "hit_count": 16,
          "hit_rate": 0.5714,
          "average_future_return": 0.005529
        },
        "5": {
          "point_type": "buy",
          "horizon_days": 5,
          "sample_count": 28,
          "hit_count": 20,
          "hit_rate": 0.7143,
          "average_future_return": 0.005286
        }
      },
      "sell": {
        "1": {
          "point_type": "sell",
          "horizon_days": 1,
          "sample_count": 762,
          "hit_count": 414,
          "hit_rate": 0.5433,
          "average_future_return": -0.000624
        },
        "3": {
          "point_type": "sell",
          "horizon_days": 3,
          "sample_count": 743,
          "hit_count": 440,
          "hit_rate": 0.5922,
          "average_future_return": -0.004443
        },
        "5": {
          "point_type": "sell",
          "horizon_days": 5,
          "sample_count": 721,
          "hit_count": 415,
          "hit_rate": 0.5756,
          "average_future_return": -0.004814
        }
      }
    }
  },
  "row_count": 20,
  "successful_count": 20,
  "failed_count": 0,
  "rows": [
    {
      "status": "ok",
      "symbol": "601919.SH",
      "name": "中远海控",
      "industry": "航运",
      "is_cycle_stock": true,
      "latest_price": 14.01,
      "change_pct": 0.21,
      "quote_time": "20260713132600",
      "quote_source": "tencent_qt_quote",
      "bar_time": "2026-07-13 13:25:00",
      "bar_count": 11647,
      "close": 14.01,
      "support": 14.01,
      "resistance": 14.14,
      "future_trend": "risk_off",
      "future_trend_label": "风险回避",
      "confidence": 68,
      "trend_state": "RANGE",
      "chan_structure_type": "divergence",
      "chan_trend_direction": "range",
      "signal": "STOP_T",
      "signal_label": "停止做 T",
      "total_score": 65.7,
      "F_score": 73.0,
      "R_score": 55.4,
      "T_score": 69.2,
      "risk_reward_ratio": 1.86,
      "sell_pressure": 4.0,
      "timing_status": "ok",
      "timing_action": "WAIT_CONFIRMATION",
      "timing_action_label": "观察",
      "timing_point_type": "watch",
      "timing_point_label": "观察",
      "buy_point_subtype": "none",
      "signal_strength_score": 20.2,
      "signal_strength_label": "无效",
      "estimated_win_rate": 0.4086,
      "up_probability_1d": 0.4282,
      "down_probability_1d": 0.5628,
      "up_probability_3d": 0.508,
      "down_probability_3d": 0.493,
      "up_probability_5d": 0.5166,
      "up_probability_5d_source": "derived_from_3d_probability_and_5_20_trend",
      "probability_state": "RANGE",
      "buy_reference_price": null,
      "sell_reference_price": null,
      "stop_price": 14.001,
      "buy_back_reference_price": null,
      "reasons": [
        "缠论结构出现卖点，主动 T 仓优先降风险。"
      ],
      "warnings": [
        "暂停 T 仓交易，只保留复盘和底仓管理。"
      ]
    },
    {
      "status": "ok",
      "symbol": "601088.SH",
      "name": "中国神华",
      "industry": "煤炭",
      "is_cycle_stock": true,
      "latest_price": 42.28,
      "change_pct": 3.1,
      "quote_time": "20260713132601",
      "quote_source": "tencent_qt_quote",
      "bar_time": "2026-07-13 13:25:00",
      "bar_count": 11167,
      "close": 42.29,
      "support": 41.91,
      "resistance": 42.3,
      "future_trend": "bearish",
      "future_trend_label": "偏弱",
      "confidence": 72,
      "trend_state": "BREAKOUT",
      "chan_structure_type": "breakout",
      "chan_trend_direction": "up",
      "signal": "SELL_T",
      "signal_label": "卖出 T 仓",
      "total_score": 62.5,
      "F_score": 73.0,
      "R_score": 47.4,
      "T_score": 68.0,
      "risk_reward_ratio": 0.03,
      "sell_pressure": 3.8,
      "timing_status": "ok",
      "timing_action": "WAIT_STRONG_TREND",
      "timing_action_label": "强趋势持有",
      "timing_point_type": "watch",
      "timing_point_label": "观察",
      "buy_point_subtype": "none",
      "signal_strength_score": 49.0,
      "signal_strength_label": "弱",
      "estimated_win_rate": 0.4948,
      "up_probability_1d": 0.5083,
      "down_probability_1d": 0.4928,
      "up_probability_3d": 0.549,
      "down_probability_3d": 0.4575,
      "up_probability_5d": 0.5636,
      "up_probability_5d_source": "derived_from_3d_probability_and_5_20_trend",
      "probability_state": "RANGE",
      "buy_reference_price": null,
      "sell_reference_price": null,
      "stop_price": 41.735,
      "buy_back_reference_price": null,
      "reasons": [
        "价格接近压力或出现放量滞涨，卖出主动仓位。",
        "盈亏比下降，卖压上升。"
      ],
      "warnings": []
    },
    {
      "status": "ok",
      "symbol": "601225.SH",
      "name": "陕西煤业",
      "industry": "煤炭",
      "is_cycle_stock": true,
      "latest_price": 23.68,
      "change_pct": 3.32,
      "quote_time": "20260713132600",
      "quote_source": "tencent_qt_quote",
      "bar_time": "2026-07-13 13:25:00",
      "bar_count": 11647,
      "close": 23.69,
      "support": 23.32,
      "resistance": 23.85,
      "future_trend": "risk_off",
      "future_trend_label": "风险回避",
      "confidence": 75,
      "trend_state": "UPTREND",
      "chan_structure_type": "divergence",
      "chan_trend_direction": "up",
      "signal": "STOP_T",
      "signal_label": "停止做 T",
      "total_score": 66.7,
      "F_score": 73.0,
      "R_score": 47.9,
      "T_score": 81.4,
      "risk_reward_ratio": 0.43,
      "sell_pressure": 3.8,
      "timing_status": "ok",
      "timing_action": "WAIT_CONFIRMATION",
      "timing_action_label": "观察",
      "timing_point_type": "watch",
      "timing_point_label": "观察",
      "buy_point_subtype": "none",
      "signal_strength_score": 49.0,
      "signal_strength_label": "弱",
      "estimated_win_rate": 0.495,
      "up_probability_1d": 0.497,
      "down_probability_1d": 0.5026,
      "up_probability_3d": 0.5634,
      "down_probability_3d": 0.4451,
      "up_probability_5d": 0.633,
      "up_probability_5d_source": "derived_from_3d_probability_and_5_20_trend",
      "probability_state": "RANGE",
      "buy_reference_price": null,
      "sell_reference_price": null,
      "stop_price": 23.279,
      "buy_back_reference_price": null,
      "reasons": [
        "缠论结构出现卖点，主动 T 仓优先降风险。"
      ],
      "warnings": [
        "暂停 T 仓交易，只保留复盘和底仓管理。"
      ]
    },
    {
      "status": "ok",
      "symbol": "600900.SH",
      "name": "长江电力",
      "industry": "电力",
      "is_cycle_stock": false,
      "latest_price": 28.31,
      "change_pct": 1.0,
      "quote_time": "20260713132601",
      "quote_source": "tencent_qt_quote",
      "bar_time": "2026-07-13 13:25:00",
      "bar_count": 11647,
      "close": 28.32,
      "support": 28.15,
      "resistance": 28.35,
      "future_trend": "bearish",
      "future_trend_label": "偏弱",
      "confidence": 78,
      "trend_state": "UPTREND",
      "chan_structure_type": "divergence",
      "chan_trend_direction": "up",
      "signal": "SELL_T",
      "signal_label": "卖出 T 仓",
      "total_score": 67.9,
      "F_score": 72.2,
      "R_score": 46.2,
      "T_score": 88.2,
      "risk_reward_ratio": 0.18,
      "sell_pressure": 3.8,
      "timing_status": "ok",
      "timing_action": "WAIT_CONFIRMATION",
      "timing_action_label": "观察",
      "timing_point_type": "watch",
      "timing_point_label": "观察",
      "buy_point_subtype": "overheat_blocked",
      "signal_strength_score": 49.0,
      "signal_strength_label": "弱",
      "estimated_win_rate": 0.4167,
      "up_probability_1d": 0.5721,
      "down_probability_1d": 0.4369,
      "up_probability_3d": 0.61,
      "down_probability_3d": 0.4046,
      "up_probability_5d": 0.7199,
      "up_probability_5d_source": "derived_from_3d_probability_and_5_20_trend",
      "probability_state": "UP_PROBABLE",
      "buy_reference_price": null,
      "sell_reference_price": null,
      "stop_price": 28.094,
      "buy_back_reference_price": null,
      "reasons": [
        "价格接近压力或出现放量滞涨，卖出主动仓位。",
        "盈亏比下降，卖压上升。"
      ],
      "warnings": []
    },
    {
      "status": "ok",
      "symbol": "600886.SH",
      "name": "国投电力",
      "industry": "电力",
      "is_cycle_stock": false,
      "latest_price": 13.92,
      "change_pct": 1.38,
      "quote_time": "20260713132601",
      "quote_source": "tencent_qt_quote",
      "bar_time": "2026-07-13 13:25:00",
      "bar_count": 11647,
      "close": 13.93,
      "support": 13.85,
      "resistance": 13.99,
      "future_trend": "risk_off",
      "future_trend_label": "风险回避",
      "confidence": 74,
      "trend_state": "UPTREND",
      "chan_structure_type": "divergence",
      "chan_trend_direction": "up",
      "signal": "STOP_T",
      "signal_label": "停止做 T",
      "total_score": 66.3,
      "F_score": 72.2,
      "R_score": 47.8,
      "T_score": 81.0,
      "risk_reward_ratio": 0.75,
      "sell_pressure": 3.8,
      "timing_status": "ok",
      "timing_action": "WAIT_CONFIRMATION",
      "timing_action_label": "观察",
      "timing_point_type": "watch",
      "timing_point_label": "观察",
      "buy_point_subtype": "none",
      "signal_strength_score": 49.0,
      "signal_strength_label": "弱",
      "estimated_win_rate": 0.5081,
      "up_probability_1d": 0.5231,
      "down_probability_1d": 0.4798,
      "up_probability_3d": 0.5844,
      "down_probability_3d": 0.4268,
      "up_probability_5d": 0.7236,
      "up_probability_5d_source": "derived_from_3d_probability_and_5_20_trend",
      "probability_state": "RANGE",
      "buy_reference_price": null,
      "sell_reference_price": null,
      "stop_price": 13.754,
      "buy_back_reference_price": null,
      "reasons": [
        "缠论结构出现卖点，主动 T 仓优先降风险。"
      ],
      "warnings": [
        "暂停 T 仓交易，只保留复盘和底仓管理。"
      ]
    },
    {
      "status": "ok",
      "symbol": "601398.SH",
      "name": "工商银行",
      "industry": "银行",
      "is_cycle_stock": false,
      "latest_price": 7.51,
      "change_pct": 2.46,
      "quote_time": "20260713132600",
      "quote_source": "tencent_qt_quote",
      "bar_time": "2026-07-13 13:25:00",
      "bar_count": 11647,
      "close": 7.5,
      "support": 7.45,
      "resistance": 7.52,
      "future_trend": "bearish",
      "future_trend_label": "偏弱",
      "confidence": 72,
      "trend_state": "BREAKOUT",
      "chan_structure_type": "breakout",
      "chan_trend_direction": "up",
      "signal": "SELL_T",
      "signal_label": "卖出 T 仓",
      "total_score": 62.1,
      "F_score": 72.2,
      "R_score": 46.0,
      "T_score": 69.0,
      "risk_reward_ratio": 0.4,
      "sell_pressure": 3.8,
      "timing_status": "ok",
      "timing_action": "WAIT",
      "timing_action_label": "等待",
      "timing_point_type": "none",
      "timing_point_label": "无信号",
      "buy_point_subtype": "overheat_blocked",
      "signal_strength_score": 49.0,
      "signal_strength_label": "弱",
      "estimated_win_rate": 0.4028,
      "up_probability_1d": 0.5,
      "down_probability_1d": 0.5,
      "up_probability_3d": 0.5773,
      "down_probability_3d": 0.433,
      "up_probability_5d": 0.6886,
      "up_probability_5d_source": "derived_from_3d_probability_and_5_20_trend",
      "probability_state": "RANGE",
      "buy_reference_price": 7.432,
      "sell_reference_price": 7.518,
      "stop_price": 7.425,
      "buy_back_reference_price": null,
      "reasons": [
        "价格接近压力或出现放量滞涨，卖出主动仓位。",
        "盈亏比下降，卖压上升。"
      ],
      "warnings": []
    },
    {
      "status": "ok",
      "symbol": "601939.SH",
      "name": "建设银行",
      "industry": "银行",
      "is_cycle_stock": false,
      "latest_price": 10.1,
      "change_pct": 2.75,
      "quote_time": "20260713132600",
      "quote_source": "tencent_qt_quote",
      "bar_time": "2026-07-13 13:25:00",
      "bar_count": 11647,
      "close": 10.1,
      "support": 10.01,
      "resistance": 10.16,
      "future_trend": "bearish",
      "future_trend_label": "偏弱",
      "confidence": 77,
      "trend_state": "BREAKOUT",
      "chan_structure_type": "breakout",
      "chan_trend_direction": "up",
      "signal": "SELL_T",
      "signal_label": "卖出 T 仓",
      "total_score": 66.6,
      "F_score": 72.2,
      "R_score": 48.2,
      "T_score": 81.5,
      "risk_reward_ratio": 0.67,
      "sell_pressure": 3.8,
      "timing_status": "ok",
      "timing_action": "WAIT",
      "timing_action_label": "等待",
      "timing_point_type": "none",
      "timing_point_label": "无信号",
      "buy_point_subtype": "none",
      "signal_strength_score": 49.0,
      "signal_strength_label": "弱",
      "estimated_win_rate": 0.491,
      "up_probability_1d": 0.4915,
      "down_probability_1d": 0.5074,
      "up_probability_3d": 0.5539,
      "down_probability_3d": 0.4533,
      "up_probability_5d": 0.6035,
      "up_probability_5d_source": "derived_from_3d_probability_and_5_20_trend",
      "probability_state": "RANGE",
      "buy_reference_price": 10.014,
      "sell_reference_price": 10.156,
      "stop_price": 9.999,
      "buy_back_reference_price": null,
      "reasons": [
        "价格接近压力或出现放量滞涨，卖出主动仓位。",
        "盈亏比下降，卖压上升。"
      ],
      "warnings": []
    },
    {
      "status": "ok",
      "symbol": "601288.SH",
      "name": "农业银行",
      "industry": "银行",
      "is_cycle_stock": false,
      "latest_price": 6.35,
      "change_pct": 1.93,
      "quote_time": "20260713132559",
      "quote_source": "tencent_qt_quote",
      "bar_time": "2026-07-13 13:25:00",
      "bar_count": 11647,
      "close": 6.35,
      "support": 6.29,
      "resistance": 6.48,
      "future_trend": "risk_off",
      "future_trend_label": "风险回避",
      "confidence": 50,
      "trend_state": "DOWNTREND",
      "chan_structure_type": "breakdown",
      "chan_trend_direction": "down",
      "signal": "STOP_T",
      "signal_label": "停止做 T",
      "total_score": 60.9,
      "F_score": 72.2,
      "R_score": 54.7,
      "T_score": 54.9,
      "risk_reward_ratio": 2.17,
      "sell_pressure": 3.8,
      "timing_status": "ok",
      "timing_action": "WAIT_CONFIRMATION",
      "timing_action_label": "观察",
      "timing_point_type": "watch",
      "timing_point_label": "观察",
      "buy_point_subtype": "none",
      "signal_strength_score": 28.5,
      "signal_strength_label": "无效",
      "estimated_win_rate": 0.4263,
      "up_probability_1d": 0.4546,
      "down_probability_1d": 0.5397,
      "up_probability_3d": 0.4865,
      "down_probability_3d": 0.5117,
      "up_probability_5d": 0.5,
      "up_probability_5d_source": "derived_from_3d_probability_and_5_20_trend",
      "probability_state": "RANGE",
      "buy_reference_price": null,
      "sell_reference_price": null,
      "stop_price": 6.285,
      "buy_back_reference_price": null,
      "reasons": [
        "技术趋势进入下跌状态，停止做 T。",
        "缠论结构跌破中枢或形成三卖，停止主动 T 仓。",
        "板块系统性走弱，停止做 T。"
      ],
      "warnings": [
        "暂停 T 仓交易，只保留复盘和底仓管理。"
      ]
    },
    {
      "status": "ok",
      "symbol": "600036.SH",
      "name": "招商银行",
      "industry": "银行",
      "is_cycle_stock": false,
      "latest_price": 37.18,
      "change_pct": 0.81,
      "quote_time": "20260713132601",
      "quote_source": "tencent_qt_quote",
      "bar_time": "2026-07-13 13:25:00",
      "bar_count": 11647,
      "close": 37.2,
      "support": 36.99,
      "resistance": 37.37,
      "future_trend": "bearish",
      "future_trend_label": "偏弱",
      "confidence": 71,
      "trend_state": "RANGE",
      "chan_structure_type": "divergence",
      "chan_trend_direction": "range",
      "signal": "SELL_T",
      "signal_label": "卖出 T 仓",
      "total_score": 66.0,
      "F_score": 72.2,
      "R_score": 43.8,
      "T_score": 84.8,
      "risk_reward_ratio": 0.81,
      "sell_pressure": 3.8,
      "timing_status": "ok",
      "timing_action": "WAIT",
      "timing_action_label": "等待",
      "timing_point_type": "none",
      "timing_point_label": "无信号",
      "buy_point_subtype": "none",
      "signal_strength_score": 42.1,
      "signal_strength_label": "无效",
      "estimated_win_rate": 0.4568,
      "up_probability_1d": 0.4692,
      "down_probability_1d": 0.527,
      "up_probability_3d": 0.4931,
      "down_probability_3d": 0.506,
      "up_probability_5d": 0.4639,
      "up_probability_5d_source": "derived_from_3d_probability_and_5_20_trend",
      "probability_state": "RANGE",
      "buy_reference_price": 36.96,
      "sell_reference_price": 37.36,
      "stop_price": 36.921,
      "buy_back_reference_price": null,
      "reasons": [
        "价格接近压力或出现放量滞涨，卖出主动仓位。",
        "盈亏比下降，卖压上升。"
      ],
      "warnings": []
    },
    {
      "status": "ok",
      "symbol": "600941.SH",
      "name": "中国移动",
      "industry": "运营商",
      "is_cycle_stock": false,
      "latest_price": 90.63,
      "change_pct": 0.72,
      "quote_time": "20260713132600",
      "quote_source": "tencent_qt_quote",
      "bar_time": "2026-07-13 13:25:00",
      "bar_count": 11647,
      "close": 90.68,
      "support": 90.13,
      "resistance": 91.01,
      "future_trend": "bearish",
      "future_trend_label": "偏弱",
      "confidence": 77,
      "trend_state": "UPTREND",
      "chan_structure_type": "pivot",
      "chan_trend_direction": "range",
      "signal": "SELL_T",
      "signal_label": "卖出 T 仓",
      "total_score": 67.5,
      "F_score": 72.2,
      "R_score": 48.9,
      "T_score": 83.7,
      "risk_reward_ratio": 0.6,
      "sell_pressure": 3.8,
      "timing_status": "ok",
      "timing_action": "WAIT",
      "timing_action_label": "等待",
      "timing_point_type": "none",
      "timing_point_label": "无信号",
      "buy_point_subtype": "none",
      "signal_strength_score": 46.3,
      "signal_strength_label": "弱",
      "estimated_win_rate": 0.4779,
      "up_probability_1d": 0.5048,
      "down_probability_1d": 0.4958,
      "up_probability_3d": 0.5047,
      "down_probability_3d": 0.4959,
      "up_probability_5d": 0.4229,
      "up_probability_5d_source": "derived_from_3d_probability_and_5_20_trend",
      "probability_state": "RANGE",
      "buy_reference_price": 90.15,
      "sell_reference_price": 90.99,
      "stop_price": 90.071,
      "buy_back_reference_price": null,
      "reasons": [
        "价格接近压力或出现放量滞涨，卖出主动仓位。",
        "盈亏比下降，卖压上升。"
      ],
      "warnings": []
    },
    {
      "status": "ok",
      "symbol": "601728.SH",
      "name": "中国电信",
      "industry": "运营商",
      "is_cycle_stock": false,
      "latest_price": 5.64,
      "change_pct": 0.0,
      "quote_time": "20260713132600",
      "quote_source": "tencent_qt_quote",
      "bar_time": "2026-07-13 13:25:00",
      "bar_count": 11647,
      "close": 5.64,
      "support": 5.62,
      "resistance": 5.65,
      "future_trend": "risk_off",
      "future_trend_label": "风险回避",
      "confidence": 67,
      "trend_state": "UPTREND",
      "chan_structure_type": "pivot",
      "chan_trend_direction": "range",
      "signal": "STOP_T",
      "signal_label": "停止做 T",
      "total_score": 60.3,
      "F_score": 72.2,
      "R_score": 48.8,
      "T_score": 59.9,
      "risk_reward_ratio": 0.35,
      "sell_pressure": 3.8,
      "timing_status": "ok",
      "timing_action": "WAIT_CONFIRMATION",
      "timing_action_label": "观察",
      "timing_point_type": "watch",
      "timing_point_label": "观察",
      "buy_point_subtype": "none",
      "signal_strength_score": 18.9,
      "signal_strength_label": "无效",
      "estimated_win_rate": 0.4097,
      "up_probability_1d": 0.4569,
      "down_probability_1d": 0.5377,
      "up_probability_3d": 0.4864,
      "down_probability_3d": 0.5118,
      "up_probability_5d": 0.4677,
      "up_probability_5d_source": "derived_from_3d_probability_and_5_20_trend",
      "probability_state": "RANGE",
      "buy_reference_price": null,
      "sell_reference_price": null,
      "stop_price": 5.615,
      "buy_back_reference_price": null,
      "reasons": [
        "缠论结构出现卖点，主动 T 仓优先降风险。"
      ],
      "warnings": [
        "暂停 T 仓交易，只保留复盘和底仓管理。"
      ]
    },
    {
      "status": "ok",
      "symbol": "600050.SH",
      "name": "中国联通",
      "industry": "运营商",
      "is_cycle_stock": false,
      "latest_price": 4.17,
      "change_pct": -0.71,
      "quote_time": "20260713132600",
      "quote_source": "tencent_qt_quote",
      "bar_time": "2026-07-13 13:25:00",
      "bar_count": 11647,
      "close": 4.17,
      "support": 4.17,
      "resistance": 4.22,
      "future_trend": "risk_off",
      "future_trend_label": "风险回避",
      "confidence": 50,
      "trend_state": "DOWNTREND",
      "chan_structure_type": "breakdown",
      "chan_trend_direction": "down",
      "signal": "STOP_T",
      "signal_label": "停止做 T",
      "total_score": 62.0,
      "F_score": 72.2,
      "R_score": 55.8,
      "T_score": 57.3,
      "risk_reward_ratio": 2.4,
      "sell_pressure": 3.8,
      "timing_status": "ok",
      "timing_action": "WAIT_CONFIRMATION",
      "timing_action_label": "观察",
      "timing_point_type": "watch",
      "timing_point_label": "观察",
      "buy_point_subtype": "none",
      "signal_strength_score": 0.0,
      "signal_strength_label": "无效",
      "estimated_win_rate": 0.38,
      "up_probability_1d": 0.3915,
      "down_probability_1d": 0.5949,
      "up_probability_3d": 0.3967,
      "down_probability_3d": 0.5896,
      "up_probability_5d": 0.2394,
      "up_probability_5d_source": "derived_from_3d_probability_and_5_20_trend",
      "probability_state": "DOWN_RISK",
      "buy_reference_price": null,
      "sell_reference_price": null,
      "stop_price": 4.166,
      "buy_back_reference_price": null,
      "reasons": [
        "技术趋势进入下跌状态，停止做 T。",
        "缠论结构跌破中枢或形成三卖，停止主动 T 仓。",
        "板块系统性走弱，停止做 T。"
      ],
      "warnings": [
        "暂停 T 仓交易，只保留复盘和底仓管理。"
      ]
    },
    {
      "status": "ok",
      "symbol": "600018.SH",
      "name": "上港集团",
      "industry": "港口",
      "is_cycle_stock": true,
      "latest_price": 5.09,
      "change_pct": 0.59,
      "quote_time": "20260713132559",
      "quote_source": "tencent_qt_quote",
      "bar_time": "2026-07-13 13:25:00",
      "bar_count": 11647,
      "close": 5.1,
      "support": 5.09,
      "resistance": 5.12,
      "future_trend": "risk_off",
      "future_trend_label": "风险回避",
      "confidence": 72,
      "trend_state": "UPTREND",
      "chan_structure_type": "divergence",
      "chan_trend_direction": "up",
      "signal": "STOP_T",
      "signal_label": "停止做 T",
      "total_score": 64.4,
      "F_score": 73.0,
      "R_score": 47.1,
      "T_score": 74.6,
      "risk_reward_ratio": 0.78,
      "sell_pressure": 3.8,
      "timing_status": "ok",
      "timing_action": "WAIT_CONFIRMATION",
      "timing_action_label": "观察",
      "timing_point_type": "watch",
      "timing_point_label": "观察",
      "buy_point_subtype": "none",
      "signal_strength_score": 49.0,
      "signal_strength_label": "弱",
      "estimated_win_rate": 0.4943,
      "up_probability_1d": 0.4886,
      "down_probability_1d": 0.5099,
      "up_probability_3d": 0.571,
      "down_probability_3d": 0.4385,
      "up_probability_5d": 0.6966,
      "up_probability_5d_source": "derived_from_3d_probability_and_5_20_trend",
      "probability_state": "RANGE",
      "buy_reference_price": null,
      "sell_reference_price": null,
      "stop_price": 5.066,
      "buy_back_reference_price": null,
      "reasons": [
        "缠论结构出现卖点，主动 T 仓优先降风险。"
      ],
      "warnings": [
        "暂停 T 仓交易，只保留复盘和底仓管理。"
      ]
    },
    {
      "status": "ok",
      "symbol": "001872.SZ",
      "name": "招商港口",
      "industry": "港口",
      "is_cycle_stock": true,
      "latest_price": 21.36,
      "change_pct": 3.94,
      "quote_time": "20260713132557",
      "quote_source": "tencent_qt_quote",
      "bar_time": "2026-07-13 13:25:00",
      "bar_count": 11647,
      "close": 21.36,
      "support": 20.8,
      "resistance": 21.49,
      "future_trend": "bearish",
      "future_trend_label": "偏弱",
      "confidence": 78,
      "trend_state": "BREAKOUT",
      "chan_structure_type": "breakout",
      "chan_trend_direction": "up",
      "signal": "SELL_T",
      "signal_label": "卖出 T 仓",
      "total_score": 67.9,
      "F_score": 73.0,
      "R_score": 47.9,
      "T_score": 85.2,
      "risk_reward_ratio": 0.23,
      "sell_pressure": 3.8,
      "timing_status": "ok",
      "timing_action": "WATCH_BREAKOUT_NEXT_DAY",
      "timing_action_label": "突破观察",
      "timing_point_type": "watch",
      "timing_point_label": "观察",
      "buy_point_subtype": "breakout_watch",
      "signal_strength_score": 49.0,
      "signal_strength_label": "弱",
      "estimated_win_rate": 0.4411,
      "up_probability_1d": 0.5054,
      "down_probability_1d": 0.4952,
      "up_probability_3d": 0.5878,
      "down_probability_3d": 0.4239,
      "up_probability_5d": 0.6568,
      "up_probability_5d_source": "derived_from_3d_probability_and_5_20_trend",
      "probability_state": "RANGE",
      "buy_reference_price": 20.922,
      "sell_reference_price": null,
      "stop_price": 20.851,
      "buy_back_reference_price": null,
      "reasons": [
        "价格接近压力或出现放量滞涨，卖出主动仓位。",
        "盈亏比下降，卖压上升。"
      ],
      "warnings": []
    },
    {
      "status": "ok",
      "symbol": "600377.SH",
      "name": "宁沪高速",
      "industry": "高速公路",
      "is_cycle_stock": false,
      "latest_price": 11.97,
      "change_pct": -0.5,
      "quote_time": "20260713132600",
      "quote_source": "tencent_qt_quote",
      "bar_time": "2026-07-13 13:25:00",
      "bar_count": 11647,
      "close": 11.96,
      "support": 11.96,
      "resistance": 12.14,
      "future_trend": "risk_off",
      "future_trend_label": "风险回避",
      "confidence": 73,
      "trend_state": "BREAKOUT",
      "chan_structure_type": "breakout",
      "chan_trend_direction": "up",
      "signal": "STOP_T",
      "signal_label": "停止做 T",
      "total_score": 73.6,
      "F_score": 72.2,
      "R_score": 68.5,
      "T_score": 81.3,
      "risk_reward_ratio": 3.01,
      "sell_pressure": 3.2,
      "timing_status": "ok",
      "timing_action": "WAIT_CONFIRMATION",
      "timing_action_label": "观察",
      "timing_point_type": "watch",
      "timing_point_label": "观察",
      "buy_point_subtype": "none",
      "signal_strength_score": 0.0,
      "signal_strength_label": "无效",
      "estimated_win_rate": 0.38,
      "up_probability_1d": 0.3758,
      "down_probability_1d": 0.6086,
      "up_probability_3d": 0.4522,
      "down_probability_3d": 0.5414,
      "up_probability_5d": 0.3612,
      "up_probability_5d_source": "derived_from_3d_probability_and_5_20_trend",
      "probability_state": "DOWN_RISK",
      "buy_reference_price": null,
      "sell_reference_price": null,
      "stop_price": 11.952,
      "buy_back_reference_price": null,
      "reasons": [
        "缠论结构出现卖点，主动 T 仓优先降风险。"
      ],
      "warnings": [
        "暂停 T 仓交易，只保留复盘和底仓管理。"
      ]
    },
    {
      "status": "ok",
      "symbol": "001965.SZ",
      "name": "招商公路",
      "industry": "高速公路",
      "is_cycle_stock": false,
      "latest_price": 9.67,
      "change_pct": 0.73,
      "quote_time": "20260713132557",
      "quote_source": "tencent_qt_quote",
      "bar_time": "2026-07-13 13:25:00",
      "bar_count": 11647,
      "close": 9.68,
      "support": 9.67,
      "resistance": 10.13,
      "future_trend": "risk_off",
      "future_trend_label": "风险回避",
      "confidence": 57,
      "trend_state": "DOWNTREND",
      "chan_structure_type": "pivot",
      "chan_trend_direction": "range",
      "signal": "STOP_T",
      "signal_label": "停止做 T",
      "total_score": 69.6,
      "F_score": 72.2,
      "R_score": 66.7,
      "T_score": 69.9,
      "risk_reward_ratio": 9.3,
      "sell_pressure": 2.7,
      "timing_status": "ok",
      "timing_action": "WAIT_CONFIRMATION",
      "timing_action_label": "观察",
      "timing_point_type": "watch",
      "timing_point_label": "观察",
      "buy_point_subtype": "none",
      "signal_strength_score": 0.0,
      "signal_strength_label": "无效",
      "estimated_win_rate": 0.38,
      "up_probability_1d": 0.4252,
      "down_probability_1d": 0.5654,
      "up_probability_3d": 0.439,
      "down_probability_3d": 0.5528,
      "up_probability_5d": 0.4061,
      "up_probability_5d_source": "derived_from_3d_probability_and_5_20_trend",
      "probability_state": "RANGE",
      "buy_reference_price": null,
      "sell_reference_price": null,
      "stop_price": 9.662,
      "buy_back_reference_price": null,
      "reasons": [
        "技术趋势进入下跌状态，停止做 T。",
        "缠论结构出现卖点，主动 T 仓优先降风险。",
        "板块系统性走弱，停止做 T。"
      ],
      "warnings": [
        "暂停 T 仓交易，只保留复盘和底仓管理。"
      ]
    },
    {
      "status": "ok",
      "symbol": "601006.SH",
      "name": "大秦铁路",
      "industry": "铁路运输",
      "is_cycle_stock": true,
      "latest_price": 4.66,
      "change_pct": -0.43,
      "quote_time": "20260713132601",
      "quote_source": "tencent_qt_quote",
      "bar_time": "2026-07-13 13:25:00",
      "bar_count": 11647,
      "close": 4.66,
      "support": 4.64,
      "resistance": 4.87,
      "future_trend": "risk_off",
      "future_trend_label": "风险回避",
      "confidence": 67,
      "trend_state": "RANGE",
      "chan_structure_type": "divergence",
      "chan_trend_direction": "down",
      "signal": "STOP_T",
      "signal_label": "停止做 T",
      "total_score": 71.7,
      "F_score": 73.0,
      "R_score": 70.5,
      "T_score": 71.7,
      "risk_reward_ratio": 9.01,
      "sell_pressure": 2.1,
      "timing_status": "ok",
      "timing_action": "STOP_T_WAIT",
      "timing_action_label": "卖点",
      "timing_point_type": "sell",
      "timing_point_label": "卖点",
      "buy_point_subtype": "none",
      "signal_strength_score": 0.0,
      "signal_strength_label": "无效",
      "estimated_win_rate": 0.38,
      "up_probability_1d": 0.4183,
      "down_probability_1d": 0.5715,
      "up_probability_3d": 0.4133,
      "down_probability_3d": 0.5752,
      "up_probability_5d": 0.2391,
      "up_probability_5d_source": "derived_from_3d_probability_and_5_20_trend",
      "probability_state": "DOWN_RISK",
      "buy_reference_price": null,
      "sell_reference_price": null,
      "stop_price": 4.635,
      "buy_back_reference_price": null,
      "reasons": [
        "缠论结构跌破中枢或形成三卖，停止主动 T 仓。"
      ],
      "warnings": [
        "暂停 T 仓交易，只保留复盘和底仓管理。"
      ]
    },
    {
      "status": "ok",
      "symbol": "600028.SH",
      "name": "中国石化",
      "industry": "石油石化",
      "is_cycle_stock": true,
      "latest_price": 4.85,
      "change_pct": 1.89,
      "quote_time": "20260713132558",
      "quote_source": "tencent_qt_quote",
      "bar_time": "2026-07-13 13:25:00",
      "bar_count": 11647,
      "close": 4.86,
      "support": 4.83,
      "resistance": 4.87,
      "future_trend": "bearish",
      "future_trend_label": "偏弱",
      "confidence": 71,
      "trend_state": "UPTREND",
      "chan_structure_type": "pivot",
      "chan_trend_direction": "range",
      "signal": "SELL_T",
      "signal_label": "卖出 T 仓",
      "total_score": 61.9,
      "F_score": 73.0,
      "R_score": 48.5,
      "T_score": 64.5,
      "risk_reward_ratio": 0.33,
      "sell_pressure": 3.8,
      "timing_status": "ok",
      "timing_action": "WAIT_STRONG_TREND",
      "timing_action_label": "强趋势持有",
      "timing_point_type": "watch",
      "timing_point_label": "观察",
      "buy_point_subtype": "none",
      "signal_strength_score": 49.0,
      "signal_strength_label": "弱",
      "estimated_win_rate": 0.4949,
      "up_probability_1d": 0.4917,
      "down_probability_1d": 0.5073,
      "up_probability_3d": 0.5695,
      "down_probability_3d": 0.4397,
      "up_probability_5d": 0.6502,
      "up_probability_5d_source": "derived_from_3d_probability_and_5_20_trend",
      "probability_state": "RANGE",
      "buy_reference_price": null,
      "sell_reference_price": null,
      "stop_price": 4.815,
      "buy_back_reference_price": null,
      "reasons": [
        "价格接近压力或出现放量滞涨，卖出主动仓位。",
        "盈亏比下降，卖压上升。"
      ],
      "warnings": []
    },
    {
      "status": "ok",
      "symbol": "601857.SH",
      "name": "中国石油",
      "industry": "石油石化",
      "is_cycle_stock": true,
      "latest_price": 9.45,
      "change_pct": 1.94,
      "quote_time": "20260713132601",
      "quote_source": "tencent_qt_quote",
      "bar_time": "2026-07-13 13:25:00",
      "bar_count": 11647,
      "close": 9.46,
      "support": 9.41,
      "resistance": 9.48,
      "future_trend": "bearish",
      "future_trend_label": "偏弱",
      "confidence": 71,
      "trend_state": "UPTREND",
      "chan_structure_type": "pivot",
      "chan_trend_direction": "range",
      "signal": "SELL_T",
      "signal_label": "卖出 T 仓",
      "total_score": 62.2,
      "F_score": 73.0,
      "R_score": 49.5,
      "T_score": 64.2,
      "risk_reward_ratio": 0.4,
      "sell_pressure": 3.8,
      "timing_status": "ok",
      "timing_action": "WAIT",
      "timing_action_label": "等待",
      "timing_point_type": "none",
      "timing_point_label": "无信号",
      "buy_point_subtype": "none",
      "signal_strength_score": 29.2,
      "signal_strength_label": "无效",
      "estimated_win_rate": 0.4306,
      "up_probability_1d": 0.4702,
      "down_probability_1d": 0.5261,
      "up_probability_3d": 0.48,
      "down_probability_3d": 0.5173,
      "up_probability_5d": 0.3748,
      "up_probability_5d_source": "derived_from_3d_probability_and_5_20_trend",
      "probability_state": "RANGE",
      "buy_reference_price": 9.333,
      "sell_reference_price": 9.477,
      "stop_price": 9.321,
      "buy_back_reference_price": null,
      "reasons": [
        "价格接近压力或出现放量滞涨，卖出主动仓位。",
        "盈亏比下降，卖压上升。"
      ],
      "warnings": []
    },
    {
      "status": "ok",
      "symbol": "002714.SZ",
      "name": "牧原股份",
      "industry": "养殖",
      "is_cycle_stock": true,
      "latest_price": 38.81,
      "change_pct": 1.76,
      "quote_time": "20260713132557",
      "quote_source": "tencent_qt_quote",
      "bar_time": "2026-07-13 13:25:00",
      "bar_count": 12175,
      "close": 38.81,
      "support": 37.91,
      "resistance": 39.14,
      "future_trend": "risk_off",
      "future_trend_label": "风险回避",
      "confidence": 65,
      "trend_state": "UPTREND",
      "chan_structure_type": "divergence",
      "chan_trend_direction": "up",
      "signal": "STOP_T",
      "signal_label": "停止做 T",
      "total_score": 60.0,
      "F_score": 73.0,
      "R_score": 46.1,
      "T_score": 61.1,
      "risk_reward_ratio": 0.37,
      "sell_pressure": 3.8,
      "timing_status": "ok",
      "timing_action": "WAIT_CONFIRMATION",
      "timing_action_label": "观察",
      "timing_point_type": "watch",
      "timing_point_label": "观察",
      "buy_point_subtype": "none",
      "signal_strength_score": 44.4,
      "signal_strength_label": "无效",
      "estimated_win_rate": 0.4818,
      "up_probability_1d": 0.4948,
      "down_probability_1d": 0.5045,
      "up_probability_3d": 0.5459,
      "down_probability_3d": 0.4602,
      "up_probability_5d": 0.7007,
      "up_probability_5d_source": "derived_from_3d_probability_and_5_20_trend",
      "probability_state": "RANGE",
      "buy_reference_price": null,
      "sell_reference_price": null,
      "stop_price": 37.836,
      "buy_back_reference_price": null,
      "reasons": [
        "缠论结构出现卖点，主动 T 仓优先降风险。"
      ],
      "warnings": [
        "暂停 T 仓交易，只保留复盘和底仓管理。"
      ]
    }
  ],
  "notice": "模型输出仅用于研究复盘，不构成投资建议。"
}
